ml-toolkit/__init__.py
ml-toolkit/_nbdev.py
ml-toolkit/core.py
mlt/__init__.py
mlt/_nbdev.py
mlt/core.py
mlt/s3.py
ml_toolkit-0.0.3.dist-info/METADATA
ml_toolkit-0.0.3.dist-info/WHEEL
ml_toolkit-0.0.3.dist-info/entry_points.txt
ml_toolkit-0.0.3.dist-info/top_level.txt
ml_toolkit-0.0.3.dist-info/RECORD
