Metadata-Version: 2.1
Name: ml-toolkit
Version: 0.0.3
Summary: 'Toolkit for ML code!'
Home-page: https://github.com/jakubLangr/mlt/tree/{branch}/
Author: Jakub
Author-email: james.langr@gmail.com
License: Full Copyright by Jakub Langr (for now)
Keywords: ML DataOps
Platform: UNKNOWN
Classifier: Development Status :: 3 - Alpha
Classifier: Intended Audience :: Developers
Classifier: Natural Language :: English
Classifier: Programming Language :: Python :: 3.6
Classifier: Programming Language :: Python :: 3.7
Classifier: Programming Language :: Python :: 3.8
Classifier: License :: Other/Proprietary License
Requires-Python: >=3.6
Requires-Dist: pip
Requires-Dist: packaging
Requires-Dist: fastcore
Requires-Dist: nbdev
Provides-Extra: dev
